context_logger/__init__.py
context_logger/logger.py
tests/__init__.py
tests/test_context_logger.py
context_log_python-0.2.1.dist-info/METADATA
context_log_python-0.2.1.dist-info/WHEEL
context_log_python-0.2.1.dist-info/top_level.txt
context_log_python-0.2.1.dist-info/RECORD
