Metadata-Version: 2.4
Name: context-log-python
Version: 0.2.1
Summary: A contextual logging framework for Python
Home-page: https://github.com/Ramakrishna9493/context_logger
Author: Ramakrishna Bapathu
Author-email: ramkrishna9493@gmail.com
License: MIT
Classifier: Programming Language :: Python :: 3
Classifier: Programming Language :: Python :: 3.7
Classifier: License :: OSI Approved :: MIT License
Classifier: Operating System :: OS Independent
Requires-Python: >=3.6
Requires-Dist: transformers>=4.55.4
Requires-Dist: torch>=2.8.0
Dynamic: author
Dynamic: author-email
Dynamic: classifier
Dynamic: description
Dynamic: description-content-type
Dynamic: home-page
Dynamic: license
Dynamic: requires-dist
Dynamic: requires-python
Dynamic: summary
